MANIFEST.in
README.txt
setup.py
medialog/.DS_Store
medialog/__init__.py
medialog.mobilethemeOne.egg-info/PKG-INFO
medialog.mobilethemeOne.egg-info/SOURCES.txt
medialog.mobilethemeOne.egg-info/dependency_links.txt
medialog.mobilethemeOne.egg-info/entry_points.txt
medialog.mobilethemeOne.egg-info/namespace_packages.txt
medialog.mobilethemeOne.egg-info/not-zip-safe
medialog.mobilethemeOne.egg-info/requires.txt
medialog.mobilethemeOne.egg-info/top_level.txt
medialog/mobilethemeOne/.DS_Store
medialog/mobilethemeOne/__init__.py
medialog/mobilethemeOne/configure.zcml
medialog/mobilethemeOne/profiles/.DS_Store
medialog/mobilethemeOne/profiles/default/.DS_Store
medialog/mobilethemeOne/profiles/default/metadata.xml
medialog/mobilethemeOne/profiles/default/theme.xml
medialog/mobilethemeOne/static/.DS_Store
medialog/mobilethemeOne/static/index.html
medialog/mobilethemeOne/static/manifest.cfg
medialog/mobilethemeOne/static/rules.xml
medialog/mobilethemeOne/static/theme.html
medialog/mobilethemeOne/static/assets/.DS_Store
medialog/mobilethemeOne/static/assets/authoring.css
medialog/mobilethemeOne/static/assets/invisibles.css
medialog/mobilethemeOne/static/assets/navigation.css
medialog/mobilethemeOne/static/assets/ploneui.css
medialog/mobilethemeOne/static/assets/reset.css
medialog/mobilethemeOne/static/assets/theme.css
medialog/mobilethemeOne/static/assets/IcoMoon/.DS_Store
medialog/mobilethemeOne/static/assets/IcoMoon/.gitignore
medialog/mobilethemeOne/static/assets/IcoMoon/License.txt
medialog/mobilethemeOne/static/assets/IcoMoon/README
medialog/mobilethemeOne/static/assets/IcoMoon/Icons/png/16px/accessibility.png
medialog/mobilethemeOne/static/assets/IcoMoon/Icons/png/16px/address-book.png
medialog/mobilethemeOne/static/assets/IcoMoon/Icons/png/16px/aid.png
medialog/mobilethemeOne/static/assets/IcoMoon/Icons/png/16px/airplane.png
medialog/mobilethemeOne/static/assets/IcoMoon/Icons/png/16px/alarm.png
medialog/mobilethemeOne/static/assets/IcoMoon/Icons/png/16px/alarm2.png
medialog/mobilethemeOne/static/assets/IcoMoon/Icons/png/16px/android.png
medialog/mobilethemeOne/static/assets/IcoMoon/Icons/png/16px/angry.png
medialog/mobilethemeOne/static/assets/IcoMoon/Icons/png/16px/angry2.png
medialog/mobilethemeOne/static/assets/IcoMoon/Icons/png/16px/apple.png
medialog/mobilethemeOne/static/assets/IcoMoon/Icons/png/16px/arrow-down-left.png
