Metadata-Version: 1.1
Name: medialog.mobilethemeOne
Version: 0.1.3
Summary: A diazo theme for zettwerk.mobiletheming
Home-page: http://github.com/espenmn/medialog.mobilethemeOne
Author: Espen Moe-Nilssen
Author-email: UNKNOWN
License: gpl
Keywords: mobiletheming plone zetterk
Platform: UNKNOWN
Classifier: Programming Language :: Python
